flowmatic/__init__.py
flowmatic/flowmatic.py
flowmatic/flows/__init__.py
flowmatic/flows/flow.py
flowmatic/forms/__init__.py
flowmatic/forms/fields/__init__.py
flowmatic/forms/fields/check_box.py
flowmatic/forms/fields/date_select.py
flowmatic/forms/fields/display.py
flowmatic/forms/fields/field.py
flowmatic/forms/fields/file_field.py
flowmatic/forms/fields/radio_group.py
flowmatic/forms/fields/text_field.py
flowmatic/forms/validation.py
flowmatic/gui/__init__.py
flowmatic/gui/constants.py
flowmatic/gui/elements/__init__.py
flowmatic/gui/elements/element_infos.py
flowmatic/gui/gui.py
flowmatic/gui/screens/__init__.py
flowmatic/gui/screens/element_screen.py
flowmatic/gui/screens/form_screen.py
flowmatic/gui/screens/menu_screen.py
flowmatic/gui/screens/result_screen.py
flowmatic/gui/screens/screen.py
flowmatic/gui/screens/title_screen.py
flowmatic/gui/style/__init__.py
flowmatic/gui/style/style.py
flowmatic/gui/tkgui.py
flowmatic/README.md
flowmatic/server.py
flowmatic/util/__init__.py
flowmatic/util/exceptions.py
flowmatic/util/icons.py
flowmatic/util/saved_class.py
flowmatic/util/settings.py
flowmatic/util/singleton.py
flowmatic/util/user.py
flowmatic-0.1.6.2.dist-info/METADATA
flowmatic-0.1.6.2.dist-info/WHEEL
flowmatic-0.1.6.2.dist-info/RECORD
